{"/*":["X-Frame-Options: DENY","X-XSS-Protection: 1; mode=block","X-Content-Type-Options: nosniff","Referrer-Policy: same-origin"],"/styles.cae504e54deb57ac0b25.css":["Cache-Control: public, max-age=31536000, immutable"],"/1bfc9850-5afb891a6b51a6fb6d49.js":["Cache-Control: public, max-age=31536000, immutable"],"/commons-42451b9a336ecdc58456.js":["Cache-Control: public, max-age=31536000, immutable"],"/component---src-pages-404-js-4b221188a7bc60b882db.js":["Cache-Control: public, max-age=31536000, immutable"],"/component---src-pages-index-js-7a464695686f94a9933d.js":["Cache-Control: public, max-age=31536000, immutable"],"/component---src-pages-projects-js-ee8a70fe206fcee8cc42.js":["Cache-Control: public, max-age=31536000, immutable"],"/webpack-runtime-c0ae37141f31ac063a03.js":["Cache-Control: public, max-age=31536000, immutable"],"/framework-ea6f2de12348a16a3fb7.js":["Cache-Control: public, max-age=31536000, immutable"],"/app-fed286c3650ba1439dd2.js":["Cache-Control: public, max-age=31536000, immutable"],"/static/*":["Cache-Control: public, max-age=31536000, immutable"],"/sw.js":["Cache-Control: public, max-age=0, must-revalidate"],"/404/":["Link: </webpack-runtime-c0ae37141f31ac063a03.js>; rel=preload; as=script; nopush","Link: </framework-ea6f2de12348a16a3fb7.js>; rel=preload; as=script; nopush","Link: </app-fed286c3650ba1439dd2.js>; rel=preload; as=script; nopush","Link: </1bfc9850-5afb891a6b51a6fb6d49.js>; rel=preload; as=script; nopush","Link: </commons-42451b9a336ecdc58456.js>; rel=preload; as=script; nopush","Link: </component---src-pages-404-js-4b221188a7bc60b882db.js>; rel=preload; as=script; nopush","Link: </page-data/app-data.json>; rel=preload; as=fetch; crossorigin; nopush","Link: </page-data/404/page-data.json>; rel=preload; as=fetch; crossorigin; nopush"],"/404.html":["Link: </webpack-runtime-c0ae37141f31ac063a03.js>; rel=preload; as=script; nopush","Link: </framework-ea6f2de12348a16a3fb7.js>; rel=preload; as=script; nopush","Link: </app-fed286c3650ba1439dd2.js>; rel=preload; as=script; nopush","Link: </1bfc9850-5afb891a6b51a6fb6d49.js>; rel=preload; as=script; nopush","Link: </commons-42451b9a336ecdc58456.js>; rel=preload; as=script; nopush","Link: </component---src-pages-404-js-4b221188a7bc60b882db.js>; rel=preload; as=script; nopush","Link: </page-data/app-data.json>; rel=preload; as=fetch; crossorigin; nopush","Link: </page-data/404.html/page-data.json>; rel=preload; as=fetch; crossorigin; nopush"],"/":["Link: </webpack-runtime-c0ae37141f31ac063a03.js>; rel=preload; as=script; nopush","Link: </framework-ea6f2de12348a16a3fb7.js>; rel=preload; as=script; nopush","Link: </app-fed286c3650ba1439dd2.js>; rel=preload; as=script; nopush","Link: </1bfc9850-5afb891a6b51a6fb6d49.js>; rel=preload; as=script; nopush","Link: </commons-42451b9a336ecdc58456.js>; rel=preload; as=script; nopush","Link: </component---src-pages-index-js-7a464695686f94a9933d.js>; rel=preload; as=script; nopush","Link: </page-data/app-data.json>; rel=preload; as=fetch; crossorigin; nopush","Link: </page-data/index/page-data.json>; rel=preload; as=fetch; crossorigin; nopush"],"/projects/":["Link: </webpack-runtime-c0ae37141f31ac063a03.js>; rel=preload; as=script; nopush","Link: </framework-ea6f2de12348a16a3fb7.js>; rel=preload; as=script; nopush","Link: </app-fed286c3650ba1439dd2.js>; rel=preload; as=script; nopush","Link: </1bfc9850-5afb891a6b51a6fb6d49.js>; rel=preload; as=script; nopush","Link: </commons-42451b9a336ecdc58456.js>; rel=preload; as=script; nopush","Link: </component---src-pages-projects-js-ee8a70fe206fcee8cc42.js>; rel=preload; as=script; nopush","Link: </page-data/app-data.json>; rel=preload; as=fetch; crossorigin; nopush","Link: </page-data/projects/page-data.json>; rel=preload; as=fetch; crossorigin; nopush"]}